orcid_downloader/__init__.py
orcid_downloader/__main__.py
orcid_downloader/api.py
orcid_downloader/cli.py
orcid_downloader/lexical.py
orcid_downloader/name_utils.py
orcid_downloader/owl.py
orcid_downloader/py.typed
orcid_downloader/ror.py
orcid_downloader/sqldb.py
orcid_downloader/standardize.py
orcid_downloader/version.py
orcid_downloader/wikidata.py
orcid_downloader-0.1.0.dist-info/licenses/LICENSE
orcid_downloader-0.1.0.dist-info/METADATA
orcid_downloader-0.1.0.dist-info/WHEEL
orcid_downloader-0.1.0.dist-info/top_level.txt
orcid_downloader-0.1.0.dist-info/RECORD
