Metadata-Version: 2.4
Name: orcid_downloader
Version: 0.1.0
Summary: Download and process ORCID in bulk
Author-email: Charles Tapley Hoyt <cthoyt@gmail.com>
Maintainer-email: Charles Tapley Hoyt <cthoyt@gmail.com>
License: MIT License
Project-URL: Bug Tracker, https://github.com/cthoyt/orcid_downloader/issues
Project-URL: Homepage, https://github.com/cthoyt/orcid_downloader
Project-URL: Repository, https://github.com/cthoyt/orcid_downloader.git
Project-URL: Documentation, https://orcid_downloader.readthedocs.io
Keywords: snekpack,cookiecutter,orcid,authorship
Classifier: Development Status :: 1 - Planning
Classifier: Environment :: Console
Classifier: Intended Audience :: Developers
Classifier: License :: OSI Approved :: MIT License
Classifier: Operating System :: OS Independent
Classifier: Framework :: Pytest
Classifier: Framework :: tox
Classifier: Framework :: Sphinx
Classifier: Programming Language :: Python
Classifier: Programming Language :: Python :: 3.12
Classifier: Programming Language :: Python :: 3 :: Only
Requires-Python: >=3.12
License-File: LICENSE
Requires-Dist: tqdm
Requires-Dist: lxml
Requires-Dist: pystow
Requires-Dist: pydantic
Requires-Dist: pydantic_extra_types[pycountry]
Requires-Dist: semantic_pydantic
Requires-Dist: bioregistry>=0.11.13
Requires-Dist: qualo>=0.0.2
Requires-Dist: wikidata_client
Provides-Extra: tests
Requires-Dist: pytest; extra == "tests"
Requires-Dist: coverage; extra == "tests"
Provides-Extra: process
Requires-Dist: pyobo>=0.12.15; extra == "process"
Requires-Dist: ssslm[gilda-slim]; extra == "process"
Requires-Dist: gilda-slim>=1.4.1.1; extra == "process"
Requires-Dist: tabulate; extra == "process"
Provides-Extra: autocomplete
Requires-Dist: ssslm[gilda-slim]; extra == "autocomplete"
Requires-Dist: fastapi; extra == "autocomplete"
Provides-Extra: docs
Requires-Dist: sphinx>=8; extra == "docs"
Requires-Dist: sphinx-rtd-theme>=3.0; extra == "docs"
Requires-Dist: sphinx_automodapi; extra == "docs"
Dynamic: license-file
